so_magic/__init__.py
so_magic/logging.conf
so_magic/so_master.py
so_magic/data/__init__.py
so_magic/data/built_in_commands.py
so_magic/data/built_in_data_manager_commands.py
so_magic/data/command_factories.py
so_magic/data/commands_manager.py
so_magic/data/data_manager.py
so_magic/data/datapoints_manager.py
so_magic/data/dataset.py
so_magic/data/discretization.py
so_magic/data/encoding.py
so_magic/data/interfaces.py
so_magic/data/magic_datapoints_factory.py
so_magic/data/pd_commands.py
so_magic/data/backend/__init__.py
so_magic/data/backend/backend.py
so_magic/data/backend/backend_specs.py
so_magic/data/backend/engine.py
so_magic/data/backend/engine_command_factory.py
so_magic/data/backend/panda_handling/__init__.py
so_magic/data/backend/panda_handling/client_code.py
so_magic/data/backend/panda_handling/df_backend.py
so_magic/data/datapoints/__init__.py
so_magic/data/datapoints/datapoints.py
so_magic/data/datapoints/tabular_data_interface.py
so_magic/data/features/__init__.py
so_magic/data/features/features.py
so_magic/data/features/features_set.py
so_magic/data/features/phi.py
so_magic/data/features/phis.py
so_magic/data/variables/__init__.py
so_magic/data/variables/types.py
so_magic/som/__init__.py
so_magic/som/factory.py
so_magic/som/manager.py
so_magic/som/self_organising_map.py
so_magic/utils/__init__.py
so_magic/utils/command_factory_interface.py
so_magic/utils/command_interface.py
so_magic/utils/commands.py
so_magic/utils/linear_mapping.py
so_magic/utils/mediator.py
so_magic/utils/memoize.py
so_magic/utils/notification.py
so_magic/utils/registry.py
so_magic/utils/singleton.py
so_magic/utils/subclass_registry.py
so_magic/utils/transformations.py
so_magic-0.7.1.dist-info/LICENSE
so_magic-0.7.1.dist-info/METADATA
so_magic-0.7.1.dist-info/WHEEL
so_magic-0.7.1.dist-info/top_level.txt
so_magic-0.7.1.dist-info/RECORD
