Metadata-Version: 2.1
Name: so-magic
Version: 0.7.1
Summary: Self Organising MAp Graceful InterfaCe
Home-page: UNKNOWN
Author: Konstantinos Lampridis
Author-email: k.lampridis@hotmail.com
License: GNU GPLv3
Download-URL: https://github.com/boromir674/so-magic/archive/v0.7.1.tar.gz
Project-URL: Issue Tracker, https://github.com/boromir674/so-magic/issues
Project-URL: Changelog, https://github.com/boromir674/so-magic/blob/master/CHANGELOG.rst
Project-URL: Source, https://github.com/boromir674/so-magic
Project-URL: Documentation, https://so-magic.readthedocs.io/
Keywords: unsupervised learning,self-organizing map
Platform: UNKNOWN
Classifier: Development Status :: 4 - Beta
Classifier: Intended Audience :: Developers
Classifier: Intended Audience :: Science/Research
Classifier: License :: OSI Approved :: GNU General Public License v3 (GPLv3)
Classifier: Natural Language :: English
Classifier: Operating System :: POSIX :: Linux
Classifier: Operating System :: MacOS
Classifier: Programming Language :: Python
Classifier: Programming Language :: Python :: 3.6
Classifier: Programming Language :: Python :: 3.7
Classifier: Programming Language :: Python :: 3.8
Classifier: Topic :: Scientific/Engineering :: Artificial Intelligence
Classifier: Topic :: Scientific/Engineering :: Information Analysis
Classifier: Topic :: Scientific/Engineering :: Visualization
Classifier: Topic :: Software Development :: Libraries :: Python Modules
License-File: LICENSE
Requires-Dist: attrs
Requires-Dist: numpy
Requires-Dist: pandas
Requires-Dist: scikit-learn
Requires-Dist: somoclu
